alibabacloud_sls20201230/__init__.py
alibabacloud_sls20201230/client.py
alibabacloud_sls20201230/models/__init__.py
alibabacloud_sls20201230/models/_agent_instance_config_gray_configs.py
alibabacloud_sls20201230/models/_alert.py
alibabacloud_sls20201230/models/_alert_configuration.py
alibabacloud_sls20201230/models/_alert_query.py
alibabacloud_sls20201230/models/_alert_tag.py
alibabacloud_sls20201230/models/_apply_config_to_machine_group_response.py
alibabacloud_sls20201230/models/_async_sql_response_data.py
alibabacloud_sls20201230/models/_azure_blob_ingestion.py
alibabacloud_sls20201230/models/_azure_blob_ingestion_configuration.py
alibabacloud_sls20201230/models/_azure_blob_ingestion_configuration_source.py
alibabacloud_sls20201230/models/_call_ai_tools_request.py
alibabacloud_sls20201230/models/_call_ai_tools_response.py
alibabacloud_sls20201230/models/_change_resource_group_request.py
alibabacloud_sls20201230/models/_change_resource_group_response.py
alibabacloud_sls20201230/models/_chart.py
alibabacloud_sls20201230/models/_condition_configuration.py
alibabacloud_sls20201230/models/_consume_processor.py
alibabacloud_sls20201230/models/_consume_processor_configuration.py
alibabacloud_sls20201230/models/_consumer_group.py
alibabacloud_sls20201230/models/_consumer_group_heart_beat_request.py
alibabacloud_sls20201230/models/_consumer_group_heart_beat_response.py
alibabacloud_sls20201230/models/_consumer_group_update_check_point_request.py
alibabacloud_sls20201230/models/_consumer_group_update_check_point_response.py
alibabacloud_sls20201230/models/_copilot_action.py
alibabacloud_sls20201230/models/_create_agent_instance_config_request.py
alibabacloud_sls20201230/models/_create_agent_instance_config_response.py
alibabacloud_sls20201230/models/_create_alert_request.py
alibabacloud_sls20201230/models/_create_alert_response.py
alibabacloud_sls20201230/models/_create_annotation_data_set_request.py
alibabacloud_sls20201230/models/_create_annotation_data_set_response.py
alibabacloud_sls20201230-5.11.1.dist-info/LICENSE
alibabacloud_sls20201230-5.11.1.dist-info/METADATA
alibabacloud_sls20201230-5.11.1.dist-info/WHEEL
alibabacloud_sls20201230-5.11.1.dist-info/top_level.txt
alibabacloud_sls20201230-5.11.1.dist-info/RECORD
